markdown_inline_graphviz.py
markdown_graphviz_inline-1.1.3.dist-info/LICENSE
markdown_graphviz_inline-1.1.3.dist-info/METADATA
markdown_graphviz_inline-1.1.3.dist-info/WHEEL
markdown_graphviz_inline-1.1.3.dist-info/top_level.txt
markdown_graphviz_inline-1.1.3.dist-info/RECORD
